yoowallet/__init__.py
yoowallet/exceptions.py
yoowallet/types.py
yoowallet/core/__init__.py
yoowallet/core/app.py
yoowallet/notifications/__init__.py
yoowallet/notifications/server.py
yoowallet/notifications/types.py
yoowallet/sync/__init__.py
yoowallet/sync/app.py
yoowallet/utils/__init__.py
yoowallet/utils/authorizer.py
yoowallet/utils/revoke.py
yoowallet-0.1.0.dist-info/LICENSE
yoowallet-0.1.0.dist-info/METADATA
yoowallet-0.1.0.dist-info/WHEEL
yoowallet-0.1.0.dist-info/top_level.txt
yoowallet-0.1.0.dist-info/RECORD
