Metadata-Version: 2.1
Name: yoowallet
Version: 0.1.0
Summary: Simple async/sync python SDK for YooMoney
Author: Shkvaldev
License: MIT
Project-URL: Documentation, https://yoowalletpy.github.io
Project-URL: Source Code, https://github.com/yoowalletpy/yoowallet
Requires-Python: >=3.8
License-File: LICENSE
Requires-Dist: aiohttp
Provides-Extra: dev
Requires-Dist: setuptools ; extra == 'dev'
Requires-Dist: mkdocs ; extra == 'dev'
Requires-Dist: mkdocstrings[python] ; extra == 'dev'
Requires-Dist: mkdocs-material ; extra == 'dev'
Provides-Extra: sync
Requires-Dist: requests ; extra == 'sync'
